PokeAPI.py
setup.cfg
setup.py
PokeAPI.py.egg-info/PKG-INFO
PokeAPI.py.egg-info/SOURCES.txt
PokeAPI.py.egg-info/dependency_links.txt
PokeAPI.py.egg-info/requires.txt
PokeAPI.py.egg-info/top_level.txt