Metadata-Version: 1.1
Name: PokeAPI.py
Version: 1.0.0
Summary: Python 3 wrapper for the unofficial PokeAPI
Home-page: https://github.com/jameswenzel/PokeAPI.py
Author: James Wenzel
Author-email: wenzel.james.r@gmail.com
License: Apache License 2.0
Download-URL: http://github.com/jameswenzel/PokeAPI.py/tarball1.0.0
Keywords: pokemon,api,pokeapi,v2
Platform: UNKNOWN
